mktestdocs/__init__.py
mktestdocs/__main__.py
mktestdocs-0.2.5.dist-info/licenses/LICENSE
mktestdocs-0.2.5.dist-info/METADATA
mktestdocs-0.2.5.dist-info/WHEEL
mktestdocs-0.2.5.dist-info/top_level.txt
mktestdocs-0.2.5.dist-info/RECORD
