Metadata-Version: 2.4
Name: mktestdocs
Version: 0.2.5
Summary: A tool for testing markdown documentation
License: MIT
Requires-Python: >=3.8
License-File: LICENSE
Provides-Extra: test
Requires-Dist: pytest; extra == "test"
Dynamic: license-file
